utils/__init__.py
utils/assets.py
utils/aws.py
utils/llm.py
utils/prompt.py
utils/py.typed
londonaicentre_mesa_utils-1.0.0.dist-info/METADATA
londonaicentre_mesa_utils-1.0.0.dist-info/WHEEL
londonaicentre_mesa_utils-1.0.0.dist-info/top_level.txt
londonaicentre_mesa_utils-1.0.0.dist-info/RECORD
