Metadata-Version: 2.4
Name: londonaicentre-mesa-utils
Version: 1.0.0
Summary: MESA utils
Author-email: "Dr. Joe Zhang" <jzhang@nhs.net>, Sophie Ratkai <s.ratkai@nhs.net>, Martin Chapman <contact@martinchapman.co.uk>
License-Expression: CC-BY-NC-ND-4.0
Requires-Python: >=3.12
Requires-Dist: boto3>=1.41.1
Requires-Dist: bs4>=0.0.2
Requires-Dist: litellm>=1.80.0
Requires-Dist: markdown>=3.10
Requires-Dist: pydantic>=2.12.5
Requires-Dist: londonaicentre-mesa-types>=1.0.0
